[
  {
    "id": "theosophy",
    "titleOriginal": "Theosophie",
    "titleZh": "神智学",
    "author": "Rudolf Steiner",
    "description": "本书从精神科学的角度，阐述了人类本性的三重结构——身体、灵魂与精神，以及死亡之后灵魂的历程与转世再生的规律。",
    "coverColor": "#4a6fa5",
    "publishedYear": 1904,
    "chapters": [
      {
        "id": "theosophy-ch1",
        "bookId": "theosophy",
        "title": "Das Wesen des Menschen",
        "titleZh": "人的本性",
        "orderIndex": 1,
        "status": "published",
        "blocks": [
          {
            "id": "th-ch1-b0",
            "blockIndex": 0,
            "blockType": "heading",
            "originalText": "Das Wesen des Menschen",
            "translationText": "人的本性",
            "scanPageRef": 1
          },
          {
            "id": "th-ch1-b1",
            "blockIndex": 1,
            "blockType": "paragraph",
            "originalText": "Dreifach ist der Mensch. Er steht mit seinem Leib in der sinnlichen Welt; durch seine Seele baut er sich seine eigene Welt; und durch seinen Geist offenbart sich ihm eine Welt, die über die beiden anderen erhaben ist.",
            "translationText": "人具有三重性。他以其身体存在于感官世界之中；通过灵魂，他为自己建造属于自己的世界；而通过精神，一个超越前两者的世界向他显现。",
            "scanPageRef": 1
          },
          {
            "id": "th-ch1-b2",
            "blockIndex": 2,
            "blockType": "paragraph",
            "originalText": "Jeder Mensch kann von sich selbst sagen: Ich bin in mir eine Welt. Aber er kann von sich auch sagen: Ich stehe in einer Welt, ich bin ein Teil von ihr. Diese beiden Tatsachen widersprechen sich nicht; sie ergänzen sich.",
            "translationText": "每个人都可以说：我自身就是一个世界。但他也可以说：我置身于一个世界之中，我是其一部分。这两个事实并不矛盾，它们相互补充。",
            "scanPageRef": 1
          },
          {
            "id": "th-ch1-b3",
            "blockIndex": 3,
            "blockType": "paragraph",
            "originalText": "Was durch die Sinne wahrgenommen werden kann, ist die physische Welt. Was durch die Seele empfunden und gedacht wird, ist die Seelenwelt. Was durch den Geist erkannt wird, ist die Geistwelt. Diese drei Welten stehen in einem bestimmten Verhältnis zueinander.",
            "translationText": "能够被感官所感知的，是物质世界。通过灵魂所感受和思考的，是灵魂世界。通过精神所认知的，是精神世界。这三个世界彼此之间处于特定的关系之中。",
            "scanPageRef": 2
          },
          {
            "id": "th-ch1-b4",
            "blockIndex": 4,
            "blockType": "quote",
            "originalText": "Der Mensch ist ein zusammengesetztes Wesen. Er gliedert sich nach dem Leib in die Natur ein; er gliedert sich nach dem Geist in die Welt des Geistes ein; er verbindet in der Seele beide Welten.",
            "translationText": "人是一个复合的存在。就身体而言，他归属于自然；就精神而言，他归属于精神世界；在灵魂中，他将两个世界联结为一体。",
            "scanPageRef": 2
          },
          {
            "id": "th-ch1-b5",
            "blockIndex": 5,
            "blockType": "paragraph",
            "originalText": "Man unterscheidet am Menschen zunächst das, was sich der äußeren Sinneswahrnehmung darbietet. Dies ist der physische Leib. Dieser hat die gleichen Stoffe und Kräfte wie die übrige «leblose» Natur; dazu aber noch Leben.",
            "translationText": "我们首先在人身上区分出那向外在感官呈现的部分，这就是物质身体。它由与其他\"无生命\"自然界相同的物质和力量构成，但除此之外还具有生命。",
            "scanPageRef": 3
          },
          {
            "id": "th-ch1-b6",
            "blockIndex": 6,
            "blockType": "paragraph",
            "originalText": "Das Zweite am Menschen ist das, was er mit den übrigen Lebewesen gemeinsam hat: das Leben. Was lebt, hat in sich eine Kraft, die nicht in der äußeren, sinnlichen Welt beobachtet werden kann. Diese Kraft nennen wir die Lebenskraft oder den Äther-Leib.",
            "translationText": "人身上的第二个要素是他与其他生命共同拥有的：生命本身。有生命的存在在自身内部拥有一种无法在外在感官世界中被观察到的力量。我们称这种力量为生命力，或以太体。",
            "scanPageRef": 3
          },
          {
            "id": "th-ch1-b7",
            "blockIndex": 7,
            "blockType": "paragraph",
            "originalText": "Das Dritte am Menschen ist das Seelische. Die Seele nimmt Eindrücke von außen auf; sie empfindet Lust und Leid, Freude und Schmerz; sie hat Wünsche, Triebe und Leidenschaften. Dies sind seelische Erlebnisse.",
            "translationText": "人身上的第三个要素是灵魂性的部分。灵魂接收来自外部的印象；它感受喜悦与悲伤、欢乐与痛苦；它有愿望、冲动与激情。这些都是灵魂的体验。",
            "scanPageRef": 4
          }
        ]
      },
      {
        "id": "theosophy-ch2",
        "bookId": "theosophy",
        "title": "Die Seelenwelt",
        "titleZh": "灵魂世界",
        "orderIndex": 2,
        "status": "published",
        "blocks": [
          {
            "id": "th-ch2-b0",
            "blockIndex": 0,
            "blockType": "heading",
            "originalText": "Die Seelenwelt",
            "translationText": "灵魂世界",
            "scanPageRef": 55
          },
          {
            "id": "th-ch2-b1",
            "blockIndex": 1,
            "blockType": "paragraph",
            "originalText": "Die Seelenwelt ist von der physischen Welt verschieden. Wer die Seelenwelt wahrnehmen will, der muss andere Organe haben als die physischen Sinne. Erst durch solche Organe wird ihm die Seelenwelt zugänglich.",
            "translationText": "灵魂世界与物质世界截然不同。想要感知灵魂世界的人，必须拥有不同于物质感官的器官。只有通过这样的器官，灵魂世界才能向他敞开。",
            "scanPageRef": 55
          },
          {
            "id": "th-ch2-b2",
            "blockIndex": 2,
            "blockType": "paragraph",
            "originalText": "In der Seelenwelt herrschen andere Gesetze als in der physischen Welt. Das Wesen der Seelenwelt ist das Erleben. Was in der physischen Welt als Ursache und Wirkung erscheint, tritt in der Seelenwelt als inneres Erlebnis auf.",
            "translationText": "灵魂世界中运行着与物质世界不同的规律。灵魂世界的本质是体验。在物质世界中表现为因与果的东西，在灵魂世界中则以内在体验的形式呈现。",
            "scanPageRef": 56
          },
          {
            "id": "th-ch2-b3",
            "blockIndex": 3,
            "blockType": "paragraph",
            "originalText": "Wie die physischen Dinge einen physischen Leib haben, so haben die seelischen Dinge einen Seelen-Leib. Dieser ist nicht weniger wirklich als der physische Leib, aber er ist anderer Art.",
            "translationText": "正如物质事物拥有物质身体，灵魂性的事物也拥有灵魂体。灵魂体与物质身体同样真实，只是性质不同。",
            "scanPageRef": 56
          }
        ]
      },
      {
        "id": "theosophy-ch3",
        "bookId": "theosophy",
        "title": "Der Geist im Menschenreiche",
        "titleZh": "人类领域中的精神",
        "orderIndex": 3,
        "status": "draft",
        "blocks": []
      }
    ],
    "category": "人智学"
  },
  {
    "id": "knowledge-of-higher-worlds",
    "titleOriginal": "Wie erlangt man Erkenntnisse der höheren Welten?",
    "titleZh": "如何获得高级世界的认知？",
    "author": "Rudolf Steiner",
    "description": "本书是史代娜精神修炼道路的系统阐述，描述了人如何通过内在修炼，逐步培育出感知灵魂与精神世界的能力。",
    "coverColor": "#7a6fa5",
    "publishedYear": 1904,
    "chapters": [
      {
        "id": "how-ch1",
        "bookId": "knowledge-of-higher-worlds",
        "title": "Wie erlangt man Erkenntnisse der höheren Welten?",
        "titleZh": "如何获得高级世界的认知？",
        "orderIndex": 1,
        "status": "published",
        "blocks": [
          {
            "id": "how-ch1-b0",
            "blockIndex": 0,
            "blockType": "heading",
            "originalText": "Wie erlangt man Erkenntnisse der höheren Welten?",
            "translationText": "如何获得高级世界的认知？",
            "scanPageRef": 1
          },
          {
            "id": "how-ch1-b1",
            "blockIndex": 1,
            "blockType": "paragraph",
            "originalText": "In jedem Menschen schlafen Fähigkeiten, durch die er Erkenntnisse über höhere Welten erlangen kann. Mystiker, Gnostiker, Theosophen redeten von einer Geisterwelt, die für sie ebenso offenbar war wie die Welt der Sinne.",
            "translationText": "每个人身上都沉睡着一些能力，通过这些能力，他可以获得关于更高世界的认知。神秘主义者、灵知主义者、神智学家们谈论一个精神世界，对他们而言，这个世界与感官世界一样真实可见。",
            "scanPageRef": 1
          },
          {
            "id": "how-ch1-b2",
            "blockIndex": 2,
            "blockType": "paragraph",
            "originalText": "Man kann sagen: wer höhere Erkenntnisse sucht, der muss zunächst Ehrfurcht und Hochachtung vor dem Wahren und dem Wirklichen in sich schaffen. Diese Hochachtung ist der Keim, aus dem die höheren Erkenntnisfähigkeiten hervorwachsen.",
            "translationText": "可以这样说：寻求更高认知的人，首先必须在自身内培育对真实与现实的敬畏与崇敬。这种崇敬是更高认知能力由以生长的种子。",
            "scanPageRef": 2
          },
          {
            "id": "how-ch1-b3",
            "blockIndex": 3,
            "blockType": "paragraph",
            "originalText": "Die Wege zu dieser höheren Erkenntnis gehen durch das innere Seelenleben des Menschen. Man muss lernen, sich in sich selbst zu vertiefen und dabei all das zurückzudrängen, was von außen kommt.",
            "translationText": "通往这种更高认知的道路，穿越人的内在灵魂生活。人必须学会深入到自身内部，同时将一切来自外部的东西推向后方。",
            "scanPageRef": 2
          }
        ]
      }
    ],
    "category": "灵修"
  },
  {
    "id": "philosophy-of-freedom",
    "titleOriginal": "Die Philosophie der Freiheit",
    "titleZh": "自由的哲学",
    "author": "Rudolf Steiner",
    "description": "本书从认识论出发，探讨人类自由的本质，论证真正的自由来自于纯粹思维活动，是史代娜哲学著作中最具系统性的一部。",
    "coverColor": "#6a8f6a",
    "publishedYear": 1894,
    "chapters": [
      {
        "id": "pof-ch1",
        "bookId": "philosophy-of-freedom",
        "title": "Das bewusste menschliche Handeln",
        "titleZh": "有意识的人类行为",
        "orderIndex": 1,
        "status": "published",
        "blocks": [
          {
            "id": "pof-ch1-b0",
            "blockIndex": 0,
            "blockType": "heading",
            "originalText": "Das bewusste menschliche Handeln",
            "translationText": "有意识的人类行为",
            "scanPageRef": 1
          },
          {
            "id": "pof-ch1-b1",
            "blockIndex": 1,
            "blockType": "paragraph",
            "originalText": "Ist der Mensch in seinem Denken und Handeln ein geistig freies Wesen, oder steht er unter dem Zwange einer rein naturgesetzlichen Notwendigkeit?",
            "translationText": "人在其思维和行动中是一个精神上自由的存在，还是处于纯粹自然法则必然性的强制之下？",
            "scanPageRef": 1
          },
          {
            "id": "pof-ch1-b2",
            "blockIndex": 2,
            "blockType": "paragraph",
            "originalText": "Es gibt kaum eine zweite Frage, über die so viel nachgedacht worden ist wie über die Frage der menschlichen Freiheit.",
            "translationText": "几乎没有第二个问题像人类自由这个问题那样被如此深入地思考过。",
            "scanPageRef": 1
          },
          {
            "id": "pof-ch1-b3",
            "blockIndex": 3,
            "blockType": "quote",
            "originalText": "Der Mensch kann nur dann als frei gelten, wenn er imstande ist, sich selbst die Gesetze seines Handelns zu geben.",
            "translationText": "只有当人能够为自己的行为立法时，他才能被视为自由的。",
            "scanPageRef": 3
          },
          {
            "id": "pof-ch1-b4",
            "blockIndex": 4,
            "blockType": "paragraph",
            "originalText": "Beobachten wir zunächst einmal, wie wir eigentlich handeln, wenn wir meinen, frei zu handeln.",
            "translationText": "让我们首先观察：当我们认为自己在自由行动时，我们究竟是如何行动的。",
            "scanPageRef": 4
          }
        ]
      },
      {
        "id": "pof-ch2",
        "bookId": "philosophy-of-freedom",
        "title": "Der Grundtrieb zur Wissenschaft",
        "titleZh": "科学的根本冲动",
        "orderIndex": 2,
        "status": "published",
        "blocks": [
          {
            "id": "pof-ch2-b0",
            "blockIndex": 0,
            "blockType": "heading",
            "originalText": "Der Grundtrieb zur Wissenschaft",
            "translationText": "科学的根本冲动",
            "scanPageRef": 10
          },
          {
            "id": "pof-ch2-b1",
            "blockIndex": 1,
            "blockType": "paragraph",
            "originalText": "In den mannigfaltigsten Formen tritt uns die Unzufriedenheit des Menschen mit dem bloß Gegebenen entgegen.",
            "translationText": "人类对于单纯给定之物的不满足感，以各种各样的形式呈现在我们面前。",
            "scanPageRef": 10
          },
          {
            "id": "pof-ch2-b2",
            "blockIndex": 2,
            "blockType": "paragraph",
            "originalText": "Wir wollen die Welt nicht nur wahrnehmen; wir wollen sie auch begreifen. Begreifen heißt: die Dinge durch Begriffe vermittelt erfassen.",
            "translationText": "我们不仅想感知世界，还想理解它。理解意味着：通过概念的中介来把握事物。",
            "scanPageRef": 11
          },
          {
            "id": "pof-ch2-b3",
            "blockIndex": 3,
            "blockType": "subheading",
            "originalText": "Das Denken als Werkzeug",
            "translationText": "思维作为工具",
            "scanPageRef": 12
          },
          {
            "id": "pof-ch2-b4",
            "blockIndex": 4,
            "blockType": "paragraph",
            "originalText": "Das Denken ist dasjenige, was uns über die bloße Wahrnehmung hinausführt. Es ist das Organ, durch das wir in das Innere der Dinge eindringen.",
            "translationText": "思维是将我们引向单纯感知之外的东西。它是我们藉以深入事物内部的器官。",
            "scanPageRef": 12
          },
          {
            "id": "pof-ch2-b5",
            "blockIndex": 5,
            "blockType": "quote",
            "originalText": "Denken ist die stille Unterhaltung des Menschen mit sich selbst über die Welt.",
            "translationText": "思维是人与自身就世界所进行的无声对话。",
            "scanPageRef": 13
          }
        ]
      }
    ],
    "category": "人智学"
  },
  {
    "id": "local-1775812380328",
    "titleOriginal": "die Würde des kleinen Kindes",
    "titleZh": "幼儿的尊严",
    "author": "Michael Glöcke ",
    "description": "儿童养育指南",
    "coverColor": "#8a6244",
    "publishedYear": 2026,
    "chapters": [
      {
        "id": "local-1775812380328-ch1",
        "bookId": "local-1775812380328",
        "title": "幼儿的自主",
        "titleZh": "幼儿的自主",
        "orderIndex": 1,
        "status": "published",
        "blocks": [
          {
            "id": "local-1775812380328-ch1-b0",
            "blockIndex": 0,
            "blockType": "paragraph",
            "originalText": "幼儿完全是“自主的奇迹”。只要我们不阻拦，他们就会靠\n自己去行动，他们非常地清楚，他们完全是自主的。只是他们\n自己不知道而已。这种条件反射的自我意识虽然还没有苏醒，\n但仍然会有意识地指导孩子的行为。\n我们去看一个艺术家的工作，就能体验到一个人呈现出的\n那种有意无意的自主性。这也是为什么我们要将艺术引入到教\n育的多重原因：例如运动课，语言课，音乐课，甚至在处理形\n状和颜色的时候。在形式，颜色，声音，文字和动作中的确存\n在着一些表达的规则。艺术有着其独立的规则，正如感官世界\n有它的规则一样。自主并非意味着无规则，相反地它意味着自\n愿的，自立的，有创造力的地处理这些必要条件和规则（希腊\n语叫做：独立立法）。自主是一种能够独立处理并灵活将规则\n转化的能力。\n这里再举一个例子：字母表中的字母是非常有限的。有一\n些语言的辅音较多，有一些则在字母表上略有减少，但是字母\n的数量往往是可控的。全球的大部分文化就是由这些少量的字\n母描述和构建出来的。数十亿计的文字！正如歌德所说，只有\n法律和规则才能赋予人们自由的意识。\n成人的自主\n第 页\n4\n在我18岁考驾照的时候，我经历了一次对我的自主的冲\n击。驾校的老师对女人颇有成见，他试图用一些不好的行为来\n纠正我的驾驶习惯。今天他的这些行为被称为“女性歧视”\n。当\n我经历了一系列“特别”对待的时候——所有错的地方总是被晒\n出来，也都会被嘲笑。我突然明白了，只要我拿到驾照，我想\n怎么开车就怎么开，我想去哪里就去哪里！——在驾驶规则之\n内我愿意怎么着都行。\n婴儿却什么也不能说出来。婴儿并不能避开一个负面的目\n光或者充满恨意的灵魂。小孩子们手无寸铁，他们的学习条件\n是受到限制的。就这方面而言，对任何一个人来说，只要他想\n要为另外一个人的发展创造适当的条件，艺术手段的使用都是\n一项至关重要的培训。这意味着，以个性化的方式使一般规则\n发挥效力，使另一方在其活动中实现自觉自主。\n自主的伤害\n在我们的讲座期间我真诚的请求大家不要在礼堂里拍照。\n这有两个原因：闪光灯和手机铃声都会打扰到大家。尽管闪光\n灯不象手机的电磁辐射一样有害健康，但是它仍然会打断我们\n的安静气氛，会影响大家的注意力和专注度。如果在道德角度\n我们表现出对他人的不尊重，我们就会伤害到别人的意愿。成\n年人是可以调整自己避免发生这种伤害的。当发生这种中断的\n时候，我们可以观察一下我们内在发生了什么。一般分为三个\n阶段：\n1. 我们被吓到，被打断。\n2. 我们在那一刻很生气，并会想说一些愚蠢的话。（可能\n会说的不好听）\n3. 你会再度安静下来，重新进入到会议当中。\n第 页\n5\n我们把这样打断别人的行为定义为现代人自主独立能力的\n丧失。很可惜，\n一个这样干扰别人的人，都不是一个自主的\n人，而是有着强烈的自我为",
            "translationText": "幼儿完全是“自主的奇迹”。只要我们不阻拦，他们就会靠\n自己去行动，他们非常地清楚，他们完全是自主的。只是他们\n自己不知道而已。这种条件反射的自我意识虽然还没有苏醒，\n但仍然会有意识地指导孩子的行为。\n我们去看一个艺术家的工作，就能体验到一个人呈现出的\n那种有意无意的自主性。这也是为什么我们要将艺术引入到教\n育的多重原因：例如运动课，语言课，音乐课，甚至在处理形\n状和颜色的时候。在形式，颜色，声音，文字和动作中的确存\n在着一些表达的规则。艺术有着其独立的规则，正如感官世界\n有它的规则一样。自主并非意味着无规则，相反地它意味着自\n愿的，自立的，有创造力的地处理这些必要条件和规则（希腊\n语叫做：独立立法）。自主是一种能够独立处理并灵活将规则\n转化的能力。\n这里再举一个例子：字母表中的字母是非常有限的。有一\n些语言的辅音较多，有一些则在字母表上略有减少，但是字母\n的数量往往是可控的。全球的大部分文化就是由这些少量的字\n母描述和构建出来的。数十亿计的文字！正如歌德所说，只有\n法律和规则才能赋予人们自由的意识。\n成人的自主\n第 页\n4\n在我18岁考驾照的时候，我经历了一次对我的自主的冲\n击。驾校的老师对女人颇有成见，他试图用一些不好的行为来\n纠正我的驾驶习惯。今天他的这些行为被称为“女性歧视”\n。当\n我经历了一系列“特别”对待的时候——所有错的地方总是被晒\n出来，也都会被嘲笑。我突然明白了，只要我拿到驾照，我想\n怎么开车就怎么开，我想去哪里就去哪里！——在驾驶规则之\n内我愿意怎么着都行。\n婴儿却什么也不能说出来。婴儿并不能避开一个负面的目\n光或者充满恨意的灵魂。小孩子们手无寸铁，他们的学习条件\n是受到限制的。就这方面而言，对任何一个人来说，只要他想\n要为另外一个人的发展创造适当的条件，艺术手段的使用都是\n一项至关重要的培训。这意味着，以个性化的方式使一般规则\n发挥效力，使另一方在其活动中实现自觉自主。\n自主的伤害\n在我们的讲座期间我真诚的请求大家不要在礼堂里拍照。\n这有两个原因：闪光灯和手机铃声都会打扰到大家。尽管闪光\n灯不象手机的电磁辐射一样有害健康，但是它仍然会打断我们\n的安静气氛，会影响大家的注意力和专注度。如果在道德角度\n我们表现出对他人的不尊重，我们就会伤害到别人的意愿。成\n年人是可以调整自己避免发生这种伤害的。当发生这种中断的\n时候，我们可以观察一下我们内在发生了什么。一般分为三个\n阶段：\n1. 我们被吓到，被打断。\n2. 我们在那一刻很生气，并会想说一些愚蠢的话。（可能\n会说的不好听）\n3. 你会再度安静下来，重新进入到会议当中。\n第 页\n5\n我们把这样打断别人的行为定义为现代人自主独立能力的\n丧失。很可惜，\n一个这样干扰别人的人，都不是一个自主的\n人，而是有着强烈的自我为"
          }
        ]
      }
    ]
  },
  {
    "id": "local-1775897182097",
    "titleOriginal": "ldjlf",
    "titleZh": "djie ",
    "author": "ljsdlfjals",
    "description": "sdjfjowjeoifpowe",
    "coverColor": "#4a6fa5",
    "publishedYear": 2026,
    "category": "人智学",
    "chapters": [
      {
        "id": "local-1775897182097-ch1",
        "bookId": "local-1775897182097",
        "title": "djlk ",
        "titleZh": "djlk ",
        "orderIndex": 1,
        "status": "published",
        "blocks": [
          {
            "id": "local-1775897182097-ch1-b0",
            "blockIndex": 0,
            "blockType": "paragraph",
            "originalText": "sljflö",
            "translationText": "sljflö"
          }
        ]
      }
    ]
  },
  {
    "id": "752c2bbd-738e-4241-8a38-d749e7920b55",
    "titleOriginal": "圣诞节期间给教师们的演讲集",
    "titleZh": "圣诞节期间给教师们的演讲集",
    "author": "Steiner",
    "description": "",
    "coverColor": "#4a6fa5",
    "publishedYear": 2026,
    "category": "教育学",
    "chapters": [
      {
        "id": "local-1775898074493-ch1",
        "bookId": "752c2bbd-738e-4241-8a38-d749e7920b55",
        "title": "第十二章",
        "titleZh": "第十二章",
        "orderIndex": 1,
        "status": "published",
        "blocks": [
          {
            "id": "local-1775898074493-ch1-b0",
            "blockIndex": 0,
            "blockType": "paragraph",
            "originalText": "12章'\n德语：\nEs dürfte meine Schilderung in den letzten Tagen auf Sie den Eindruck gemacht haben, daß gerade die auf anthroposophische Menschenerkenntnis begründete Erziehungs- und Unterrichtskunst in allererster Linie das physisch-leibliche Element im Menschen berücksichtigt.",
            "translationText": "12章'\n德语：\nEs dürfte meine Schilderung in den letzten Tagen auf Sie den Eindruck gemacht haben, daß gerade die auf anthroposophische Menschenerkenntnis begründete Erziehungs- und Unterrichtskunst in allererster Linie das physisch-leibliche Element im Menschen berücksichtigt."
          },
          {
            "id": "local-1775898074493-ch1-b1",
            "blockIndex": 1,
            "blockType": "paragraph",
            "originalText": "中文：\n我这几天的阐述，或许会让您产生这样一种印象：正是建立在人智学人类认识基础上的教育与教学艺术，首先关注的是人身上的物质—身体层面。",
            "translationText": "中文：\n我这几天的阐述，或许会让您产生这样一种印象：正是建立在人智学人类认识基础上的教育与教学艺术，首先关注的是人身上的物质—身体层面。"
          },
          {
            "id": "local-1775898074493-ch1-b2",
            "blockIndex": 2,
            "blockType": "paragraph",
            "originalText": "⸻",
            "translationText": "⸻"
          },
          {
            "id": "local-1775898074493-ch1-b3",
            "blockIndex": 3,
            "blockType": "paragraph",
            "originalText": "德语：\nDenn Sie werden bemerkt haben, daß ich mich bemühte zu zeigen: wie kommen wir mit unserer Erziehungskunst am besten der freien Entfaltung der vom Haupte des Menschen ausgehenden, am eigenen Organismus arbeitenden plastischen Kräfte zu Hilfe?",
            "translationText": "德语：\nDenn Sie werden bemerkt haben, daß ich mich bemühte zu zeigen: wie kommen wir mit unserer Erziehungskunst am besten der freien Entfaltung der vom Haupte des Menschen ausgehenden, am eigenen Organismus arbeitenden plastischen Kräfte zu Hilfe?"
          },
          {
            "id": "local-1775898074493-ch1-b4",
            "blockIndex": 4,
            "blockType": "paragraph",
            "originalText": "中文：\n因为您可能已经注意到，我一直在努力说明：我们如何通过教育艺术，最有效地帮助那些从人的头部出发、在自身有机体中运作的塑造性力量得到自由发展？",
            "translationText": "中文：\n因为您可能已经注意到，我一直在努力说明：我们如何通过教育艺术，最有效地帮助那些从人的头部出发、在自身有机体中运作的塑造性力量得到自由发展？"
          },
          {
            "id": "local-1775898074493-ch1-b5",
            "blockIndex": 5,
            "blockType": "paragraph",
            "originalText": "⸻",
            "translationText": "⸻"
          },
          {
            "id": "local-1775898074493-ch1-b6",
            "blockIndex": 6,
            "blockType": "paragraph",
            "originalText": "继续如下：",
            "translationText": "继续如下："
          },
          {
            "id": "local-1775898074493-ch1-b7",
            "blockIndex": 7,
            "blockType": "paragraph",
            "originalText": "⸻",
            "translationText": "⸻"
          },
          {
            "id": "local-1775898074493-ch1-b8",
            "blockIndex": 8,
            "blockType": "paragraph",
            "originalText": "德语：\nWie kommen wir gerade bei der schulmäßigen Erziehung dem Atmungs-, dem Zirkulationssystem entgegen? Wie können wir berücksichtigen, daß sich die Muskelkräfte in der freiesten Weise ausbilden?",
            "translationText": "德语：\nWie kommen wir gerade bei der schulmäßigen Erziehung dem Atmungs-, dem Zirkulationssystem entgegen? Wie können wir berücksichtigen, daß sich die Muskelkräfte in der freiesten Weise ausbilden?"
          },
          {
            "id": "local-1775898074493-ch1-b9",
            "blockIndex": 9,
            "blockType": "paragraph",
            "originalText": "中文：\n特别是在学校教育中，我们如何顺应呼吸系统和循环系统的发展？我们如何才能顾及到肌肉力量能够以最自由的方式得到形成？",
            "translationText": "中文：\n特别是在学校教育中，我们如何顺应呼吸系统和循环系统的发展？我们如何才能顾及到肌肉力量能够以最自由的方式得到形成？"
          },
          {
            "id": "local-1775898074493-ch1-b10",
            "blockIndex": 10,
            "blockType": "paragraph",
            "originalText": "⸻",
            "translationText": "⸻"
          },
          {
            "id": "local-1775898074493-ch1-b11",
            "blockIndex": 11,
            "blockType": "paragraph",
            "originalText": "德语：\nWie können wir berücksichtigen, daß sich in einer richtigen Weise die Muskeln an die Knochen ansetzen und der Mensch so in einer entsprechenden Weise physisch-leiblich in die Außenwelt hineingestellt ist?",
            "translationText": "德语：\nWie können wir berücksichtigen, daß sich in einer richtigen Weise die Muskeln an die Knochen ansetzen und der Mensch so in einer entsprechenden Weise physisch-leiblich in die Außenwelt hineingestellt ist?"
          },
          {
            "id": "local-1775898074493-ch1-b12",
            "blockIndex": 12,
            "blockType": "paragraph",
            "originalText": "中文：\n我们如何考虑到肌肉能够以正确的方式附着在骨骼上，从而使人以恰当的身体状态被安置于外部世界之中？",
            "translationText": "中文：\n我们如何考虑到肌肉能够以正确的方式附着在骨骼上，从而使人以恰当的身体状态被安置于外部世界之中？"
          },
          {
            "id": "local-1775898074493-ch1-b13",
            "blockIndex": 13,
            "blockType": "paragraph",
            "originalText": "⸻",
            "translationText": "⸻"
          },
          {
            "id": "local-1775898074493-ch1-b14",
            "blockIndex": 14,
            "blockType": "paragraph",
            "originalText": "德语：\nEs sieht so aus, als ob alles dasjenige, was von dieser hier besprochenen pädagogischen Kunst ausgeht, insofern es seelische, geistige Maßnahmen sind, so orientiert würde, daß man die möglichst gesunde und normale physisch-leibliche Entwicklung des Menschen zustande bringt.",
            "translationText": "德语：\nEs sieht so aus, als ob alles dasjenige, was von dieser hier besprochenen pädagogischen Kunst ausgeht, insofern es seelische, geistige Maßnahmen sind, so orientiert würde, daß man die möglichst gesunde und normale physisch-leibliche Entwicklung des Menschen zustande bringt."
          },
          {
            "id": "local-1775898074493-ch1-b15",
            "blockIndex": 15,
            "blockType": "paragraph",
            "originalText": "中文：\n看起来，这里所讨论的教育艺术的一切出发点，即便是心灵与精神层面的措施，也都是以促成尽可能健康、正常的人体发展为导向的。",
            "translationText": "中文：\n看起来，这里所讨论的教育艺术的一切出发点，即便是心灵与精神层面的措施，也都是以促成尽可能健康、正常的人体发展为导向的。"
          },
          {
            "id": "local-1775898074493-ch1-b16",
            "blockIndex": 16,
            "blockType": "paragraph",
            "originalText": "⸻",
            "translationText": "⸻"
          },
          {
            "id": "local-1775898074493-ch1-b17",
            "blockIndex": 17,
            "blockType": "paragraph",
            "originalText": "德语：\nUnd das ist auch so. Tatsächlich ist das vollbewußte Ziel desjenigen, was hier als gesunde Pädagogik und Didaktik angesehen werden muß: in der freiesten Weise das Physisch-Leibliche des Menschen zu entwickeln und dem Geistig-Seelischen gewissermaßen die Möglichkeit zu bieten, sich aus sich selbst heraus zu entfalten.",
            "translationText": "德语：\nUnd das ist auch so. Tatsächlich ist das vollbewußte Ziel desjenigen, was hier als gesunde Pädagogik und Didaktik angesehen werden muß: in der freiesten Weise das Physisch-Leibliche des Menschen zu entwickeln und dem Geistig-Seelischen gewissermaßen die Möglichkeit zu bieten, sich aus sich selbst heraus zu entfalten."
          },
          {
            "id": "local-1775898074493-ch1-b18",
            "blockIndex": 18,
            "blockType": "paragraph",
            "originalText": "中文：\n而事实也正是如此。这里被视为健康的教育学与教学法，其明确的目标在于：以最自由的方式发展人的身体性，同时为精神—心灵提供一种可能，使其能够从自身之中自然展开。",
            "translationText": "中文：\n而事实也正是如此。这里被视为健康的教育学与教学法，其明确的目标在于：以最自由的方式发展人的身体性，同时为精神—心灵提供一种可能，使其能够从自身之中自然展开。"
          },
          {
            "id": "local-1775898074493-ch1-b19",
            "blockIndex": 19,
            "blockType": "paragraph",
            "originalText": "⸻",
            "translationText": "⸻"
          },
          {
            "id": "local-1775898074493-ch1-b20",
            "blockIndex": 20,
            "blockType": "paragraph",
            "originalText": "如果你愿意，我可以把最后一段也全部翻译完（这页还剩一小部分）。",
            "translationText": "如果你愿意，我可以把最后一段也全部翻译完（这页还剩一小部分）。"
          }
        ]
      }
    ]
  },
  {
    "id": "53282344-4837-4355-b7c2-12ea3fbe66ea",
    "titleZh": "幼儿的尊严",
    "titleOriginal": "幼儿的尊严",
    "author": "Michael Glöcke 等",
    "description": "一本集合实操和哲学深度的育儿灵魂读本。译者：王芬",
    "coverColor": "#4a6fa5",
    "publishedYear": 2026,
    "chapters": [
      {
        "id": "5fa94a7b-ce9b-4ac4-ac20-db822d19a7c6",
        "bookId": "53282344-4837-4355-b7c2-12ea3fbe66ea",
        "title": "",
        "titleZh": "",
        "orderIndex": 0,
        "status": "published",
        "blocks": []
      }
    ]
  }
]